otelmini/__about__.py
otelmini/__init__.py
otelmini/encode.py
otelmini/trace.py
otelmini-0.0.1.dist-info/METADATA
otelmini-0.0.1.dist-info/WHEEL
otelmini-0.0.1.dist-info/licenses/LICENSE.txt
otelmini-0.0.1.dist-info/RECORD
