Metadata-Version: 2.3
Name: otelmini
Version: 0.0.1
Project-URL: Documentation, https://github.com/pmcollins/otelmini#readme
Project-URL: Issues, https://github.com/unknown/otelmini/issues
Project-URL: Source, https://github.com/unknown/otelmini
Author-email: Pablo Collins <pcollins@splunk.com>
License-Expression: Apache-2.0
License-File: LICENSE.txt
Classifier: Development Status :: 4 - Beta
Classifier: Programming Language :: Python
Classifier: Programming Language :: Python :: 3.8
Classifier: Programming Language :: Python :: 3.9
Classifier: Programming Language :: Python :: 3.10
Classifier: Programming Language :: Python :: 3.11
Classifier: Programming Language :: Python :: 3.12
Classifier: Programming Language :: Python :: Implementation :: CPython
Classifier: Programming Language :: Python :: Implementation :: PyPy
Requires-Python: >=3.8
Requires-Dist: googleapis-common-protos
Requires-Dist: grpcio
Requires-Dist: opentelemetry-api
Requires-Dist: opentelemetry-proto
Requires-Dist: opentelemetry-sdk
Requires-Dist: oteltest
